base_private/__init__.py
base_private/tests.py
base_private-1.0.1.dist-info/LICENSE
base_private-1.0.1.dist-info/WHEEL
base_private-1.0.1.dist-info/METADATA
base_private-1.0.1.dist-info/RECORD
